[
    {
        "regionId": "cnfaic_summit",
        "displayName": "Summit Lake",
        "URL": "http://www.cnfaic.org/advisories/current_summit.php",
        "points": [
            {
                "lat": "60.584",
                "lon": "-149.630"
            },
            {
                "lat": "60.550",
                "lon": "-149.538"
            },
            {
                "lat": "60.554",
                "lon": "-149.436"
            },
            {
                "lat": "60.566",
                "lon": "-149.318"
            },
            {
                "lat": "60.601",
                "lon": "-149.306"
            },
            {
                "lat": "60.649",
                "lon": "-149.326"
            },
            {
                "lat": "60.680",
                "lon": "-149.376"
            },
            {
                "lat": "60.758",
                "lon": "-149.425"
            },
            {
                "lat": "60.782",
                "lon": "-149.503"
            },
            {
                "lat": "60.760",
                "lon": "-149.544"
            },
            {
                "lat": "60.731",
                "lon": "-149.549"
            },
            {
                "lat": "60.707",
                "lon": "-149.586"
            },
            {
                "lat": "60.674",
                "lon": "-149.587"
            },
            {
                "lat": "60.659",
                "lon": "-149.631"
            },
            {
                "lat": "60.637",
                "lon": "-149.620"
            },
            {
                "lat": "60.602",
                "lon": "-149.640"
            },
            {
                "lat": "60.591",
                "lon": "-149.617"
            },
            {
                "lat": "60.584",
                "lon": "-149.630"
            }
        ]
    },
    {
        "regionId": "cnfaic_turnagain",
        "displayName": "Turnagain Pass",
        "URL": "http://www.cnfaic.org/advisories/current.php",
        "points": [
            {
                "lat": "60.876",
                "lon": "-149.255"
            },
            {
                "lat": "60.857",
                "lon": "-149.278"
            },
            {
                "lat": "60.840",
                "lon": "-149.270"
            },
            {
                "lat": "60.796",
                "lon": "-149.390"
            },
            {
                "lat": "60.758",
                "lon": "-149.424"
            },
            {
                "lat": "60.680",
                "lon": "-149.374"
            },
            {
                "lat": "60.650",
                "lon": "-149.325"
            },
            {
                "lat": "60.600",
                "lon": "-149.305"
            },
            {
                "lat": "60.566",
                "lon": "-149.316"
            },
            {
                "lat": "60.589",
                "lon": "-149.166"
            },
            {
                "lat": "60.623",
                "lon": "-149.121"
            },
            {
                "lat": "60.680",
                "lon": "-149.092"
            },
            {
                "lat": "60.679",
                "lon": "-149.014"
            },
            {
                "lat": "60.738",
                "lon": "-148.926"
            },
            {
                "lat": "60.756",
                "lon": "-148.869"
            },
            {
                "lat": "60.810",
                "lon": "-148.814"
            },
            {
                "lat": "60.826",
                "lon": "-148.823"
            },
            {
                "lat": "60.890",
                "lon": "-148.790"
            },
            {
                "lat": "60.947",
                "lon": "-148.832"
            },
            {
                "lat": "60.955",
                "lon": "-148.886"
            },
            {
                "lat": "60.987",
                "lon": "-148.941"
            },
            {
                "lat": "61.041",
                "lon": "-148.965"
            },
            {
                "lat": "61.039",
                "lon": "-149.051"
            },
            {
                "lat": "61.054",
                "lon": "-149.084"
            },
            {
                "lat": "61.050",
                "lon": "-149.140"
            },
            {
                "lat": "61.038",
                "lon": "-149.169"
            },
            {
                "lat": "61.026",
                "lon": "-149.155"
            },
            {
                "lat": "61.015",
                "lon": "-149.212"
            },
            {
                "lat": "60.981",
                "lon": "-149.181"
            },
            {
                "lat": "60.965",
                "lon": "-149.207"
            },
            {
                "lat": "60.876",
                "lon": "-149.255"
            }
        ]
    }
]